README.md
setup.cfg
setup.py
fantasy_data/FantasyData.py
fantasy_data/__init__.py
fantasy_data.egg-info/PKG-INFO
fantasy_data.egg-info/SOURCES.txt
fantasy_data.egg-info/dependency_links.txt
fantasy_data.egg-info/requires.txt
fantasy_data.egg-info/top_level.txt