Metadata-Version: 1.1
Name: fantasy-data
Version: 2.1.3
Summary: FantasyData Python
Home-page: https://fantasyfootballcalculator.com/fantasydata-python
Author: Fantasy Football Calculator
Author-email: support@fantasyfootballcalculator.com
License: UNKNOWN
Download-URL: https://github.com/ffcalculator/fantasydata-python/archive/v2.1.3.tar.gz
Keywords: fantasy,sports,football,nba
Platform: UNKNOWN
